concordex/__init__.py
concordex/neighbors/__init__.py
concordex/neighbors/_neighborhood.py
concordex/tests/test_label_utils.py
concordex/tools/__init__.py
concordex/tools/_concordex.py
concordex/utils/_labels.py
concordex-2.0.0.dist-info/licenses/LICENSE
concordex-2.0.0.dist-info/METADATA
concordex-2.0.0.dist-info/WHEEL
concordex-2.0.0.dist-info/top_level.txt
concordex-2.0.0.dist-info/RECORD
