Metadata-Version: 2.4
Name: concordex
Version: 2.0.0
Summary: Identification of spatial homogeneous regions with concordex
Home-page: https://github.com/pachterlab/concordex
Author: Kayla Jackson, A. Sina Booeshaghi, Angel Galvez-Merchan, Alexandra Kim
Author-email: Kayla Jackson <kaylajac@caltech.edu>, "A. Sina Booeshaghi" <sinab@berkeley.edu>, Angel Galvez-Merchan <angelgalvez94@gmail.com>, Alexandra Kim <alexandrasuriya@gmail.com>
Maintainer: Kayla Jackson
Maintainer-email: Kayla Jackson <kaylajac@caltech.edu>
License: MIT License
Project-URL: Repository, https://github.com/pachterlab/concordex
Keywords: SingleCell,Clustering,Spatial,Transcriptomics
Classifier: Environment :: Console
Classifier: Intended Audience :: Science/Research
Classifier: License :: OSI Approved :: MIT License
Classifier: Operating System :: OS Independent
Classifier: Programming Language :: Python :: 3.6
Classifier: Programming Language :: Python :: 3.7
Classifier: Programming Language :: Python :: 3.8
Classifier: Programming Language :: Python :: 3.9
Classifier: Programming Language :: Python :: 3.10
Classifier: Topic :: Scientific/Engineering :: Bio-Informatics
Classifier: Topic :: Utilities
Requires-Python: >=3.9
License-File: LICENSE
Requires-Dist: anndata>=0.8
Requires-Dist: numpy>=1.23
Requires-Dist: pandas>=1.5
Requires-Dist: scikit-learn>=0.24
Dynamic: license-file
